{"words":[{"text":"LP","log":[{"time":1750033375299,"rating":4,"stability":1.5,"difficulty":2.5},{"time":1750033386881,"rating":4,"stability":2.25,"difficulty":2},{"time":1750033470062,"rating":4,"stability":3.375,"difficulty":1.5},{"time":1750033475194,"rating":4,"stability":5.0625,"difficulty":1}]},{"text":"eel","log":[]},{"text":"Br.","log":[]},{"text":"rod","log":[]},{"text":"nut","log":[]},{"text":"bog","log":[]},{"text":"ego","log":[]},{"text":"mar","log":[]},{"text":"wee","log":[]},{"text":"rib","log":[]},{"text":"bud","log":[]},{"text":"R&D","log":[]},{"text":"dub","log":[]},{"text":"lag","log":[]},{"text":"pal","log":[]},{"text":"rue","log":[]},{"text":"rub","log":[]},{"text":"ace","log":[]},{"text":"pat","log":[]},{"text":"rev","log":[]}],"current":1}